<?xml version="1.0" encoding="UTF-8" standalone="yes"?>
<dgm:layoutDef xmlns:dgm="http://schemas.openxmlformats.org/drawingml/2006/diagram" xmlns:a="http://schemas.openxmlformats.org/drawingml/2006/main" uniqueId="urn:microsoft.com/office/officeart/2009/3/layout/PlusandMinus"><dgm:title val=""/><dgm:desc val=""/><dgm:catLst><dgm:cat type="relationship" pri="3600"/></dgm:catLst><dgm:sampData><dgm:dataModel><dgm:ptLst><dgm:pt modelId="0" type="doc"/><dgm:pt modelId="10"><dgm:prSet phldr="1"/></dgm:pt><dgm:pt modelId="20"><dgm:prSet phldr="1"/></dgm:pt></dgm:ptLst><dgm:cxnLst><dgm:cxn modelId="30" srcId="0" destId="10" srcOrd="0" destOrd="0"/><dgm:cxn modelId="40" srcId="0" destId="20" srcOrd="1" destOrd="0"/></dgm:cxnLst><dgm:bg/><dgm:whole/></dgm:dataModel></dgm:sampData><dgm:styleData><dgm:dataModel><dgm:ptLst><dgm:pt modelId="0" type="doc"/><dgm:pt modelId="10"><dgm:prSet phldr="1"/></dgm:pt><dgm:pt modelId="20"><dgm:prSet phldr="1"/></dgm:pt></dgm:ptLst><dgm:cxnLst><dgm:cxn modelId="30" srcId="0" destId="10" srcOrd="0" destOrd="0"/><dgm:cxn modelId="40" srcId="0" destId="20" srcOrd="1" destOrd="0"/></dgm:cxnLst><dgm:bg/><dgm:whole/></dgm:dataModel></dgm:styleData><dgm:clrData><dgm:dataModel><dgm:ptLst><dgm:pt modelId="0" type="doc"/><dgm:pt modelId="10"><dgm:prSet phldr="1"/></dgm:pt><dgm:pt modelId="20"><dgm:prSet phldr="1"/></dgm:pt></dgm:ptLst><dgm:cxnLst><dgm:cxn modelId="30" srcId="0" destId="10" srcOrd="0" destOrd="0"/><dgm:cxn modelId="40" srcId="0" destId="20" srcOrd="1" destOrd="0"/></dgm:cxnLst><dgm:bg/><dgm:whole/></dgm:dataModel></dgm:clrData><dgm:layoutNode name="Name0"><dgm:varLst><dgm:chMax val="2"/><dgm:chPref val="2"/><dgm:dir/><dgm:animOne/><dgm:resizeHandles val="exact"/></dgm:varLst><dgm:alg type="composite"><dgm:param type="ar" val="1.8238"/></dgm:alg><dgm:shape xmlns:r="http://schemas.openxmlformats.org/officeDocument/2006/relationships" r:blip=""><dgm:adjLst/></dgm:shape><dgm:choose name="Name1"><dgm:if name="Name2" func="var" arg="dir" op="equ" val="norm"><dgm:constrLst><dgm:constr type="primFontSz" for="des" ptType="node" op="equ" val="65"/><dgm:constr type="l" for="ch" forName="Background" refType="w" fact="0.09"/><dgm:constr type="t" for="ch" forName="Background" refType="h" fact="0.1641"/><dgm:constr type="w" for="ch" forName="Background" refType="w" fact="0.87"/><dgm:constr type="h" for="ch" forName="Background" refType="h" fact="0.82"/><dgm:constr type="l" for="ch" forName="ParentText1" refType="w" fact="0.116"/><dgm:constr type="t" for="ch" forName="ParentText1" refType="h" fact="0.26"/><dgm:constr type="w" for="ch" forName="ParentText1" refType="w" fact="0.404"/><dgm:constr type="h" for="ch" forName="ParentText1" refType="h" fact="0.7015"/><dgm:constr type="l" for="ch" forName="ParentText2" refType="w" fact="0.529"/><dgm:constr type="t" for="ch" forName="ParentText2" refType="h" fact="0.26"/><dgm:constr type="w" for="ch" forName="ParentText2" refType="w" fact="0.404"/><dgm:constr type="h" for="ch" forName="ParentText2" refType="h" fact="0.7015"/><dgm:constr type="l" for="ch" forName="Plus" refType="w" fact="0"/><dgm:constr type="t" for="ch" forName="Plus" refType="h" fact="0"/><dgm:constr type="w" for="ch" forName="Plus" refType="w" fact="0.17"/><dgm:constr type="h" for="ch" forName="Plus" refType="w" refFor="ch" refForName="Plus"/><dgm:constr type="l" for="ch" forName="Minus" refType="w" fact="0.84"/><dgm:constr type="t" for="ch" forName="Minus" refType="h" fact="0.1115"/><dgm:constr type="w" for="ch" forName="Minus" refType="w" fact="0.16"/><dgm:constr type="h" for="ch" forName="Minus" refType="h" fact="0.1"/><dgm:constr type="l" for="ch" forName="Divider" refType="w" fact="0.525"/><dgm:constr type="t" for="ch" forName="Divider" refType="h" fact="0.2615"/><dgm:constr type="w" for="ch" forName="Divider" refType="w" fact="0.0001"/><dgm:constr type="h" for="ch" forName="Divider" refType="h" fact="0.67"/></dgm:constrLst></dgm:if><dgm:else name="Name3"><dgm:constrLst><dgm:constr type="primFontSz" for="des" ptType="node" op="equ" val="65"/><dgm:constr type="r" for="ch" forName="Background" refType="w" fact="-0.09"/><dgm:constr type="t" for="ch" forName="Background" refType="h" fact="0.1641"/><dgm:constr type="w" for="ch" forName="Background" refType="w" fact="0.87"/><dgm:constr type="h" for="ch" forName="Background" refType="h" fact="0.82"/><dgm:constr type="r" for="ch" forName="ParentText1" refType="w" fact="-0.116"/><dgm:constr type="t" for="ch" forName="ParentText1" refType="h" fact="0.26"/><dgm:constr type="w" for="ch" forName="ParentText1" refType="w" fact="0.404"/><dgm:constr type="h" for="ch" forName="ParentText1" refType="h" fact="0.7015"/><dgm:constr type="r" for="ch" forName="ParentText2" refType="w" fact="-0.529"/><dgm:constr type="t" for="ch" forName="ParentText2" refType="h" fact="0.26"/><dgm:constr type="w" for="ch" forName="ParentText2" refType="w" fact="0.404"/><dgm:constr type="h" for="ch" forName="ParentText2" refType="h" fact="0.7015"/><dgm:constr type="r" for="ch" forName="Plus" refType="w" fact="0"/><dgm:constr type="t" for="ch" forName="Plus" refType="h" fact="0"/><dgm:constr type="w" for="ch" forName="Plus" refType="w" fact="0.17"/><dgm:constr type="h" for="ch" forName="Plus" refType="w" refFor="ch" refForName="Plus"/><dgm:constr type="r" for="ch" forName="Minus" refType="w" fact="-0.84"/><dgm:constr type="t" for="ch" forName="Minus" refType="h" fact="0.1115"/><dgm:constr type="w" for="ch" forName="Minus" refType="w" fact="0.16"/><dgm:constr type="h" for="ch" forName="Minus" refType="h" fact="0.1"/><dgm:constr type="r" for="ch" forName="Divider" refType="w" fact="-0.525"/><dgm:constr type="t" for="ch" forName="Divider" refType="h" fact="0.2615"/><dgm:constr type="w" for="ch" forName="Divider" refType="w" fact="0.0001"/><dgm:constr type="h" for="ch" forName="Divider" refType="h" fact="0.67"/></dgm:constrLst></dgm:else></dgm:choose><dgm:layoutNode name="Background" styleLbl="bgImgPlace1"><dgm:alg type="sp"/><dgm:shape type="rect" xmlns:r="http://schemas.openxmlformats.org/officeDocument/2006/relationships" r:blip=""><dgm:adjLst/></dgm:shape><dgm:presOf/></dgm:layoutNode><dgm:layoutNode name="ParentText1" styleLbl="revTx"><dgm:varLst><dgm:chMax val="0"/><dgm:chPref val="0"/><dgm:bulletEnabled val="1"/></dgm:varLst><dgm:alg type="tx"><dgm:param type="parTxLTRAlign" val="l"/><dgm:param type="txAnchorVert" val="t"/></dgm:alg><dgm:shape type="rect" xmlns:r="http://schemas.openxmlformats.org/officeDocument/2006/relationships" r:blip=""><dgm:adjLst/></dgm:shape><dgm:presOf axis="ch desOrSelf" ptType="node node" st="1 1" cnt="1 0"/><dgm:constrLst><dgm:constr type="lMarg" refType="primFontSz" fact="0.15"/><dgm:constr type="rMarg" refType="primFontSz" fact="0.15"/><dgm:constr type="tMarg" refType="primFontSz" fact="0.15"/><dgm:constr type="bMarg" refType="primFontSz" fact="0.15"/></dgm:constrLst><dgm:ruleLst><dgm:rule type="primFontSz" val="5" fact="NaN" max="NaN"/></dgm:ruleLst></dgm:layoutNode><dgm:layoutNode name="ParentText2" styleLbl="revTx"><dgm:varLst><dgm:chMax val="0"/><dgm:chPref val="0"/><dgm:bulletEnabled val="1"/></dgm:varLst><dgm:alg type="tx"><dgm:param type="parTxLTRAlign" val="l"/><dgm:param type="txAnchorVert" val="t"/></dgm:alg><dgm:shape type="rect" xmlns:r="http://schemas.openxmlformats.org/officeDocument/2006/relationships" r:blip=""><dgm:adjLst/></dgm:shape><dgm:presOf axis="ch desOrSelf" ptType="node node" st="2 1" cnt="1 0"/><dgm:constrLst><dgm:constr type="lMarg" refType="primFontSz" fact="0.15"/><dgm:constr type="rMarg" refType="primFontSz" fact="0.15"/><dgm:constr type="tMarg" refType="primFontSz" fact="0.15"/><dgm:constr type="bMarg" refType="primFontSz" fact="0.15"/></dgm:constrLst><dgm:ruleLst><dgm:rule type="primFontSz" val="5" fact="NaN" max="NaN"/></dgm:ruleLst></dgm:layoutNode><dgm:layoutNode name="Plus" styleLbl="alignNode1"><dgm:alg type="sp"/><dgm:shape type="plus" xmlns:r="http://schemas.openxmlformats.org/officeDocument/2006/relationships" r:blip=""><dgm:adjLst><dgm:adj idx="1" val="0.3281"/></dgm:adjLst></dgm:shape><dgm:presOf/></dgm:layoutNode><dgm:layoutNode name="Minus" styleLbl="alignNode1"><dgm:alg type="sp"/><dgm:shape type="rect" xmlns:r="http://schemas.openxmlformats.org/officeDocument/2006/relationships" r:blip=""><dgm:adjLst/></dgm:shape><dgm:presOf/></dgm:layoutNode><dgm:layoutNode name="Divider" styleLbl="parChTrans1D1"><dgm:alg type="sp"/><dgm:shape type="line" xmlns:r="http://schemas.openxmlformats.org/officeDocument/2006/relationships" r:blip=""><dgm:adjLst/></dgm:shape><dgm:presOf/></dgm:layoutNode></dgm:layoutNode></dgm:layoutDef>